tests/__init__.py
tests/test_tty_ov.py
tty_ov/__init__.py
tty_ov/__main__.py
tty_ov/hl_ls.py
tty_ov/tty_ov.py
tty_ov-1.0.115.dist-info/licenses/LICENSE
tty_ov-1.0.115.dist-info/METADATA
tty_ov-1.0.115.dist-info/WHEEL
tty_ov-1.0.115.dist-info/top_level.txt
tty_ov-1.0.115.dist-info/RECORD
