Metadata-Version: 2.4
Name: tty_ov
Version: 1.0.115
Summary: A module that emulates a few core functionalities of a tty (see the inner help for a list of functions).
Home-page: https://github.com/Hanra-s-work/tty_ov
Author: Henry Letellier
Author-email: henrysoftwarehouse@protonmail.com
Classifier: Programming Language :: Python :: 3
Classifier: License :: OSI Approved :: MIT License
Classifier: Operating System :: OS Independent
License-File: LICENSE
Requires-Dist: colorama==0.4.6
Requires-Dist: prettytable==3.17.0
Requires-Dist: ask_question==1.2.12
Requires-Dist: colourise-output==1.1.6
Requires-Dist: prompt-toolkit==3.0.52
Dynamic: author
Dynamic: author-email
Dynamic: classifier
Dynamic: description
Dynamic: description-content-type
Dynamic: home-page
Dynamic: license-file
Dynamic: requires-dist
Dynamic: summary
